[
    {
        "anonymous": false,
        "inputs": [
            {
                "indexed": true,
                "internalType": "uint256",
                "name": "issueId",
                "type": "uint256"
            },
            {
                "indexed": true,
                "internalType": "address",
                "name": "admin",
                "type": "address"
            },
            {
                "indexed": false,
                "internalType": "uint256",
                "name": "amount",
                "type": "uint256"
            },
            {
                "indexed": false,
                "internalType": "uint256",
                "name": "remainingFunds",
                "type": "uint256"
            },
            {
                "indexed": false,
                "internalType": "uint256",
                "name": "timestamp",
                "type": "uint256"
            }
        ],
        "name": "FundsWithdrawn",
        "type": "event"
    },
    {
        "anonymous": false,
        "inputs": [
            {
                "indexed": true,
                "internalType": "uint256",
                "name": "issueId",
                "type": "uint256"
            },
            {
                "indexed": true,
                "internalType": "address",
                "name": "confirmedBy",
                "type": "address"
            },
            {
                "indexed": false,
                "internalType": "uint256",
                "name": "confirmationCount",
                "type": "uint256"
            },
            {
                "indexed": false,
                "internalType": "uint256",
                "name": "timestamp",
                "type": "uint256"
            }
        ],
        "name": "IssueConfirmed",
        "type": "event"
    },
    {
        "anonymous": false,
        "inputs": [
            {
                "indexed": true,
                "internalType": "uint256",
                "name": "issueId",
                "type": "uint256"
            },
            {
                "indexed": true,
                "internalType": "address",
                "name": "funder",
                "type": "address"
            },
            {
                "indexed": false,
                "internalType": "uint256",
                "name": "amount",
                "type": "uint256"
            },
            {
                "indexed": false,
                "internalType": "uint256",
                "name": "totalfunding",
                "type": "uint256"
            },
            {
                "indexed": false,
                "internalType": "uint256",
                "name": "timestamp",
                "type": "uint256"
            }
        ],
        "name": "IssueFunded",
        "type": "event"
    },
    {
        "anonymous": false,
        "inputs": [
            {
                "indexed": true,
                "internalType": "uint256",
                "name": "issueId",
                "type": "uint256"
            },
            {
                "indexed": true,
                "internalType": "address",
                "name": "reporter",
                "type": "address"
            },
            {
                "indexed": false,
                "internalType": "string",
                "name": "location",
                "type": "string"
            },
            {
                "indexed": false,
                "internalType": "string",
                "name": "description",
                "type": "string"
            },
            {
                "indexed": false,
                "internalType": "string",
                "name": "imageHash",
                "type": "string"
            },
            {
                "indexed": false,
                "internalType": "uint256",
                "name": "timestamp",
                "type": "uint256"
            }
        ],
        "name": "IssueReported",
        "type": "event"
    },
    {
        "anonymous": false,
        "inputs": [
            {
                "indexed": true,
                "internalType": "uint256",
                "name": "issueId",
                "type": "uint256"
            },
            {
                "indexed": true,
                "internalType": "address",
                "name": "updatedBy",
                "type": "address"
            },
            {
                "indexed": false,
                "internalType": "uint8",
                "name": "newStatus",
                "type": "uint8"
            },
            {
                "indexed": false,
                "internalType": "uint256",
                "name": "timestamp",
                "type": "uint256"
            }
        ],
        "name": "IssueStatusUpdated",
        "type": "event"
    },
    {
        "inputs": [],
        "name": "admin",
        "outputs": [
            {
                "internalType": "address",
                "name": "",
                "type": "address"
            }
        ],
        "stateMutability": "view",
        "type": "function"
    },
    {
        "inputs": [
            {
                "internalType": "uint256",
                "name": "_issueId",
                "type": "uint256"
            }
        ],
        "name": "confirmIssue",
        "outputs": [],
        "stateMutability": "nonpayable",
        "type": "function"
    },
    {
        "inputs": [
            {
                "internalType": "uint256",
                "name": "_issueId",
                "type": "uint256"
            },
            {
                "internalType": "uint256",
                "name": "_amount",
                "type": "uint256"
            }
        ],
        "name": "fundIssue",
        "outputs": [],
        "stateMutability": "nonpayable",
        "type": "function"
    },
    {
        "inputs": [],
        "name": "getAllIssues",
        "outputs": [
            {
                "internalType": "uint256[]",
                "name": "",
                "type": "uint256[]"
            }
        ],
        "stateMutability": "view",
        "type": "function"
    },
    {
        "inputs": [
            {
                "internalType": "uint256",
                "name": "_issueId",
                "type": "uint256"
            }
        ],
        "name": "getConfirmationCount",
        "outputs": [
            {
                "internalType": "uint256",
                "name": "",
                "type": "uint256"
            }
        ],
        "stateMutability": "view",
        "type": "function"
    },
    {
        "inputs": [
            {
                "internalType": "uint256",
                "name": "_issueId",
                "type": "uint256"
            }
        ],
        "name": "getIssue",
        "outputs": [
            {
                "internalType": "uint256",
                "name": "id",
                "type": "uint256"
            },
            {
                "internalType": "address",
                "name": "reporter",
                "type": "address"
            },
            {
                "internalType": "string",
                "name": "location",
                "type": "string"
            },
            {
                "internalType": "string",
                "name": "description",
                "type": "string"
            },
            {
                "internalType": "string",
                "name": "imageHash",
                "type": "string"
            },
            {
                "internalType": "uint8",
                "name": "status",
                "type": "uint8"
            },
            {
                "internalType": "uint256",
                "name": "timestamp",
                "type": "uint256"
            }
        ],
        "stateMutability": "view",
        "type": "function"
    },
    {
        "inputs": [],
        "name": "getIssueCount",
        "outputs": [
            {
                "internalType": "uint256",
                "name": "",
                "type": "uint256"
            }
        ],
        "stateMutability": "view",
        "type": "function"
    },
    {
        "inputs": [
            {
                "internalType": "uint256",
                "name": "_issueId",
                "type": "uint256"
            }
        ],
        "name": "getIssueFunding",
        "outputs": [
            {
                "internalType": "uint256",
                "name": "totalFunding",
                "type": "uint256"
            },
            {
                "internalType": "uint256",
                "name": "fundsUsed",
                "type": "uint256"
            },
            {
                "internalType": "uint256",
                "name": "available",
                "type": "uint256"
            }
        ],
        "stateMutability": "view",
        "type": "function"
    },
    {
        "inputs": [
            {
                "internalType": "uint256",
                "name": "_issueId",
                "type": "uint256"
            },
            {
                "internalType": "address",
                "name": "_user",
                "type": "address"
            }
        ],
        "name": "getUserFunding",
        "outputs": [
            {
                "internalType": "uint256",
                "name": "",
                "type": "uint256"
            }
        ],
        "stateMutability": "view",
        "type": "function"
    },
    {
        "inputs": [
            {
                "internalType": "uint256",
                "name": "_issueId",
                "type": "uint256"
            },
            {
                "internalType": "address",
                "name": "_user",
                "type": "address"
            }
        ],
        "name": "hasUserConfirmed",
        "outputs": [
            {
                "internalType": "bool",
                "name": "",
                "type": "bool"
            }
        ],
        "stateMutability": "view",
        "type": "function"
    },
    {
        "inputs": [],
        "name": "issueCount",
        "outputs": [
            {
                "internalType": "uint256",
                "name": "",
                "type": "uint256"
            }
        ],
        "stateMutability": "view",
        "type": "function"
    },
    {
        "inputs": [
            {
                "internalType": "string",
                "name": "_location",
                "type": "string"
            },
            {
                "internalType": "string",
                "name": "_description",
                "type": "string"
            },
            {
                "internalType": "string",
                "name": "_imageHash",
                "type": "string"
            }
        ],
        "name": "reportIssue",
        "outputs": [
            {
                "internalType": "uint256",
                "name": "",
                "type": "uint256"
            }
        ],
        "stateMutability": "nonpayable",
        "type": "function"
    },
    {
        "inputs": [
            {
                "internalType": "uint256",
                "name": "_issueId",
                "type": "uint256"
            },
            {
                "internalType": "uint8",
                "name": "_newStatus",
                "type": "uint8"
            }
        ],
        "name": "updateIssueStatus",
        "outputs": [],
        "stateMutability": "nonpayable",
        "type": "function"
    },
    {
        "inputs": [
            {
                "internalType": "uint256",
                "name": "_issueId",
                "type": "uint256"
            },
            {
                "internalType": "uint256",
                "name": "_amount",
                "type": "uint256"
            }
        ],
        "name": "withdrawFunds",
        "outputs": [],
        "stateMutability": "nonpayable",
        "type": "function"
    }
]